Workbook

Sheet Sheet1
A1: Order ID | B1: Order Date | C1: Customer Name | D1: Country | E1: City | F1: Product Category | G1: Product Name | H1: Quantity | I1: Unit Price | J1: Discount | K1: Total Sales | L1: Payment Method | M1: Order Status | N1: Delivery Date | O1: Customer Rating
A2: ORD1001 | B2: 45798 | C2: Peter Johnson | D2: NIGERIA | E2: Lagos | F2: Electronics | G2: ELEC-1002-Y-Bluetooth Speaker | H2: 3 | I2: 370.87 | J2: 20 | K2: 890.09 | L2: Credit Card | M2: delivered | N2: 45802 | O2: 1
A3: ORD1002 | B3: 45945 | C3: Daniel Anderson | D3: UK | E3: London | F3: Beauty | G3: BEAU-4001-C-Face Serum | H3: 7 | I3: 118.02 | J3: 20 | K3: 660.91 | L3: creditcard | M3: Shipped | N3: 45949 | O3: 3
A4: ORD1003 | B4: 45768 | C4: Aisha Garcia | D4: Ghana | E4: Accra | F4: Electronic | G4: HOME-2001-A-Air Fryer | H4: 2 | I4: 55.45 | J4: 0 | K4: 110.9 | L4: Credit Card | M4: Shipped | N4: 45781 | O4: 3
A5: ORD1004 | B5: 45698 | C5: Daniel Johnson | D5: South Africa | E5: Cape Town | F5: Electronics | G5: HOME-2001-A-Air Fryer | H5: 10 | I5: 443.87 | J5: 10 | K5: 3994.83 | L5: Credit Card | M5: Shipped | N5: 45707 | O5: 5
A6: ORD1005 | B6: 45777 | C6: Ahmed Garcia | D6: nigeria | E6: Kano | F6: electronics | G6: ELEC-1001-X-Wireless Mouse | H6: 7 | I6: 146.21 | J6: 10 | K6: 921.12 | L6: Cash | M6: Complete | N6: 45791 | O6: 2
A7: ORD1006 | B7: 45931 | C7: Grace Thomas | D7: Kenya | E7: Nairobi | F7: Electronic | G7: ELEC-1002-Y-Bluetooth Speaker | H7: 3 | I7: 236.51 | J7: 10 | K7: 638.58 | L7: Credit Card | M7: delivered | N7: 45943 | O7: 5
A8: ORD1007 | B8: 45795 | C8: Ahmed Rauf | D8: United Kingdom | E8: London | F8: fashion | G8: ELEC-1002-Y-Bluetooth Speaker | H8: 10 | I8: 439.42 | J8: 10 | K8: 3954.78 | L8: PayPal | M8: delivered | N8: 45797 | O8: 2
A9: ORD1008 | B9: 45933 | C9: David Wilson | D9: Kenya | E9: Nairobi | F9: Fashion | G9: BEAU-4001-C-Face Serum | H9: 7 | I9: 449.93 | J9: 15 | K9: 2677.08 | L9: PayPal | M9: Delivered | N9: 45938 | O9: 3
A10: ORD1009 | B10: 45979 | C10: Sophia Johnson | D10: United Kingdom | E10: London | F10: Electronic | G10: FASH-3001-B-Running Shoes | H10: 10 | I10: 41.13 | J10: 15 | K10: 349.61 | L10: Bank Transfer | M10: Delivered | N10: 45982 | O10: 5
A11: ORD1010 | B11: 25/11/2025 | C11: Peter Taylor | D11: Ghana | E11: Accra | F11: Beauty | G11: ELEC-1001-X-Wireless Mouse | H11: 5 | I11: 223.03 | J11: 15 | K11: 947.88 | L11: creditcard | M11: Cancelled | N11: 45992 | O11: 1
A12: ORD1011 | B12: 45985 | C12: Sophia Thomas | D12: Nigeria | E12: Kano | F12: Electronic | G12: BEAU-4001-C-Face Serum | H12: 4 | I12: 84.89 | J12: 5 | K12: 322.58 | L12: PayPal | M12: Delivered | N12: 45994 | O12: 5
A13: ORD1012 | B13: 45780 | C13: Samuel Rauf | D13: United Kingdom | E13: London | F13: Fashion | G13: ELEC-1002-Y-Bluetooth Speaker | H13: 10 | I13: 474.01 | J13: 0 | K13: 4740.1 | L13: creditcard | M13: delivered | N13: 45781 | O13: 4
A14: ORD1013 | B14: 45928 | C14: Daniel Brown | D14: Kenya | E14: Nairobi | F14: fashion | G14: BEAU-4001-C-Face Serum | H14: 7 | I14: 482.54 | J14: 20 | K14: 2702.22 | L14: Cash | M14: Complete | N14: 45942 | O14: 2
A15: ORD1014 | B15: 45719 | C15: Samuel Taylor | D15: Ghana | E15: Accra | F15: electronics | G15: ELEC-1002-Y-Bluetooth Speaker | H15: 2 | I15: 175.66 | J15: 20 | K15: 281.06 | L15: Credit Card | M15: Delivered | N15: 45723 | O15: 5
A16: ORD1014 | B16: 45719 | C16: Samuel Taylor | D16: Ghana | E16: Accra | F16: electronics | G16: ELEC-1002-Y-Bluetooth Speaker | H16: 2 | I16: 175.66 | J16: 20 | K16: 281.06 | L16: Credit Card | M16: Delivered | N16: 45723 | O16: 5
A17: ORD1015 | B17: 45827 | C17: Sarah Johnson | D17: NIGERIA | E17: Lagos | F17: Fashion | G17: BEAU-4001-C-Face Serum | H17: 4 | I17: 146.45 | J17: 15 | K17: 497.93 | L17: Bank Transfer | M17: Pending | N17: 45829 | O17: 2
A18: ORD1016 | B18: 45755 | C18: Ahmed Davis | D18: Nigeria | E18: Lagos | F18: fashion | G18: ELEC-1001-X-Wireless Mouse | H18: 7 | I18: 183.61 | J18: 15 | K18: 1092.48 | L18: Cash | M18: Delivered | N18: 45757 | O18: 4
A19: ORD1017 | B19: 45713 | C19: James Martin | D19: NIGERIA | E19: Kano | F19: Home & Kitchen | G19: ELEC-1002-Y-Bluetooth Speaker | H19: 4 | I19: 272.78 | J19: 5 | K19: 1036.56 | L19: creditcard | M19: Delivered | N19: 45717 | O19: 4
A20: ORD1018 | B20: 45683 | C20: Ahmed Taylor | D20: UK | E20: London | F20: Home & Kitchen | G20: BEAU-4001-C-Face Serum | H20: -2 | I20: 484.81 | J20: 5 | K20: -921.14 | L20: creditcard | M20: Pending | N20: 45694 | O20: 2
A21: ORD1019 | B21: 45857 | C21: David Miller | D21: NIGERIA | E21: Abuja | F21: Electronic | G21: FASH-3001-B-Running Shoes | H21: 5 | I21: 217.27 | J21: 20 | K21: 869.08 | L21: creditcard | M21: Delivered | N21: 45862 | O21: 4
A22: ORD1020 | B22: 45936 | C22: Linda Taylor | D22: Ghana | E22: Accra | F22: Electronics | G22: ELEC-1001-X-Wireless Mouse | H22: 10 | I22: 243.63 | J22: 20 | K22: 1949.04 | L22: creditcard | M22: Delivered | N22: 45819
A23: ORD1021 | B23: 45864 | C23: Mary Thomas | D23: kenya | E23: Nairobi | F23: fashion | G23: BEAU-4001-C-Face Serum | H23: 4 | I23: 293.67 | J23: 0 | K23: 1174.68 | L23: Bank Transfer | M23: Cancelled | N23: 45866 | O23: 5
A24: ORD1022 | B24: 46000 | C24: Aisha Garcia | D24: United Kingdom | E24: London | F24: Beauty | G24: HOME-2001-A-Air Fryer | H24: 4 | I24: 140.15 | J24: 150 | K24: -280.3 | L24: Credit Card | M24: Delivered | N24: 46012 | O24: 3
A25: ORD1023 | B25: 45695 | C25: grace anderson | D25: niGERIA | E25: Kano | F25: Electronic | G25: ELEC-1002-Y-Bluetooth Speaker | H25: 9 | I25: 139.95 | J25: 10 | K25: 1133.6 | L25: creditcard | M25: Pending | N25: 45704 | O25: 1
A26: ORD1024 | B26: 45992 | C26: Linda Garcia | D26: Ghana | E26: Accra | F26: Electronics | G26: ELEC-1001-X-Wireless Mouse | H26: 9 | I26: 156.7 | J26: 0 | K26: 1410.3 | L26: Cash | M26: Cancelled | N26: 46001 | O26: 8
A27: ORD1025 | B27: 45765 | C27: Michael Garcia | D27: United Kingdom | E27: London | F27: Beauty | G27: HOME-2001-A-Air Fryer | H27: 4 | I27: 346.87 | J27: 10 | K27: 1248.73 | L27: Credit Card | M27: Delivered | N27: 45762 | O27: 5
A28: ORD1026 | B28: 45658 | C28: Sophia Garcia | D28: UK | E28: London | F28: Electronics | G28: ELEC-1002-Y-Bluetooth Speaker | H28: 0 | I28: 89.18 | J28: 15 | K28: 0 | L28: Credit Card | M28: Delivered | N28: 45665 | O28: 5
A29: ORD1027 | B29: 45956 | C29: Daniel Smith | D29: Nigeria | E29: Kano | F29: electronics | G29: ELEC-1002-Y-Bluetooth Speaker | H29: 7 | I29: 72.45 | J29: 10 | K29: 456.44 | L29: Cash | M29: delivered | O29: 3
A30: ORD1028 | B30: 45975 | D30: Nigeria | E30: Abuja | F30: fashion | G30: ELEC-1002-Y-Bluetooth Speaker | H30: 4 | I30: 433.66 | J30: 5 | K30: 1647.91 | L30: Credit-card | M30: Pending | N30: 45987 | O30: 4
A31: ORD1006 | B31: 45931 | C31: Grace Thomas | D31: South Africa | E31: Cape Town | F31: Electronic | G31: ELEC-1002-Y-Bluetooth Speaker | H31: 3 | I31: 236.51 | J31: 10 | K31: 638.58 | L31: Credit Card | M31: delivered | N31: 45943 | O31: 5
A32: ORD1029 | B32: 45853 | C32: MICHAEL BROWN | D32: Ghana | E32: Accra | F32: Beauty | G32: ELEC-1001-X-Wireless Mouse | H32: 8 | I32: 118.99 | J32: 15 | K32: 809.13 | L32: creditcard | M32: delivered | N32: 45867 | O32: 3
A33: ORD1030 | B33: 18/06/2025 | C33: Peter Wilson | D33: South Africa | E33: Cape Town | F33: Electronics | G33: ELEC-1001-X-Wireless Mouse | H33: 5 | I33: 182.06 | J33: 20 | K33: 728.24 | L33: Credit-card | M33: delivered | N33: 45831 | O33: 4
A34: ORD1031 | B34: 45963 | C34: Michael Smith | D34: Ghana | E34: Accra | F34: electronics | G34: HOME-2001-A-Air Fryer | H34: 6 | I34: 223.83 | J34: 20 | K34: 1074.38 | L34: Credit-card | M34: Delivered | N34: 45970 | O34: 1
A35: ORD1032 | B35: 46009 | C35: John Taylor | D35: South Africa | E35: Cape Town | F35: Beauty | G35: ELEC-1002-Y-Bluetooth Speaker | H35: 6 | I35: 221.34 | J35: 10 | K35: 1195.24 | L35: Credit Card | M35: Shipped | N35: 46021 | O35: 5
A36: ORD1033 | B36: 45658 | C36: Daniel Garcia | D36: UK | E36: London | F36: fashion | G36: FASH-3001-B-Running Shoes | H36: 5 | I36: 281.66 | J36: 5 | K36: 1337.89 | L36: creditcard | M36: Cancelled | N36: 45873 | O36: 4
A37: ORD1034 | B37: 45658 | C37: Michael Miller | D37: Kenya | E37: Nairobi | F37: Home & Kitchen | G37: HOME-2001-A-Air Fryer | H37: 4 | I37: 220.65 | J37: 20 | K37: 706.08 | L37: PayPal | M37: Shipped | N37: 45663 | O37: 5
A38: ORD1035 | B38: 45995 | C38: Daniel Davis | D38: nigeria | E38: Lagos | F38: Beauty | G38: HOME-2001-A-Air Fryer | H38: 9 | I38: 335.29 | J38: 20 | K38: 2414.09 | L38: creditcard | M38: Shipped | N38: 45997 | O38: 3
A39: ORD1036 | B39: 45670 | C39: Sarah Wilson | D39: UK | E39: London | F39: Fashion | G39: ELEC-1002-Y-Bluetooth Speaker | H39: -2 | I39: 309.52 | J39: 0 | K39: -619.04 | L39: creditcard | M39: Shipped | N39: 45671 | O39: 4
A40: ORD1037 | B40: 45733 | C40: Fatima Miller | D40: United Kingdom | E40: London | F40: Fashion | G40: ELEC-1001-X-Wireless Mouse | H40: 2 | I40: 391.43 | J40: 5 | K40: 743.72 | L40: creditcard | M40: Delivered | N40: 45744 | O40: 2
A41: ORD1038 | B41: 45929 | C41: David Davis | D41: UK | E41: London | F41: Fashion | G41: BEAU-4001-C-Face Serum | H41: 6 | I41: 475.52 | J41: 15 | K41: 2425.15 | L41: PayPal | M41: delivered | N41: 45938 | O41: 5
A42: ORD1039 | B42: 45984 | C42: Fatima Garcia | D42: South Africa | E42: Cape Town | F42: Electronic | G42: BEAU-4001-C-Face Serum | H42: 8 | I42: 317.11 | J42: 10 | K42: 2283.19 | L42: creditcard | M42: Complete | N42: 45989 | O42: 4
A43: ORD1040 | B43: 45994 | C43: Aisha Taylor | D43: kenya | E43: Nairobi | F43: Electronic | G43: ELEC-1002-Y-Bluetooth Speaker | H43: 7 | I43: 350.04 | J43: 5 | K43: 2327.77 | L43: Bank Transfer | M43: Pending | N43: 45731
A44: ORD1041 | B44: 45857 | C44: John Wilson | D44: NIGERIA | E44: Lagos | F44: Electronic | G44: BEAU-4001-C-Face Serum | H44: 1 | I44: 429.8 | J44: 20 | K44: 343.84 | L44: Credit-card | M44: Pending | N44: 45870 | O44: 4
A45: ORD1042 | B45: 45966 | C45: Daniel Martin | D45: UK | E45: London | F45: fashion | G45: FASH-3001-B-Running Shoes | H45: 4 | I45: 143.74 | J45: 15 | K45: 488.72 | L45: Cash | M45: Pending | N45: 45970 | O45: 1
A46: ORD1031 | B46: 45963 | C46: Michael Smith | D46: Ghana | E46: Accra | F46: electronics | G46: HOME-2001-A-Air Fryer | H46: 6 | I46: 223.83 | J46: 20 | K46: 1074.38 | L46: Credit-card | M46: Delivered | N46: 45970 | O46: 1
A47: ORD1043 | B47: 45976 | C47: Sophia Davis | D47: nigeria | E47: Abuja | F47: Beauty | G47: ELEC-1001-X-Wireless Mouse | H47: 7 | I47: 300.03 | J47: 0 | K47: 2100.21 | L47: PayPal | M47: delivered | N47: 45985 | O47: 1
A48: ORD1044 | B48: 45766 | C48: Michael Miller | D48: United Kingdom | E48: London | F48: Beauty | G48: HOME-2001-A-Air Fryer | H48: 6 | I48: 383 | J48: 150 | K48: -1149 | L48: Credit Card | M48: Pending | N48: 45774 | O48: 3
A49: ORD1045 | B49: 45837 | C49: Linda Taylor | D49: Ghana | E49: Accra | F49: electronics | G49: ELEC-1001-X-Wireless Mouse | H49: 1 | I49: 379.57 | J49: 5 | K49: 360.59 | L49: creditcard | M49: delivered | N49: 45841 | O49: 2
A50: ORD1046 | B50: 45769 | C50: peter johnson | D50: NIGERIA | E50: Kano | F50: Electronics | G50: HOME-2001-A-Air Fryer | H50: 6 | I50: 92.22 | J50: 20 | K50: 442.66 | L50: Bank Transfer | M50: Delivered | N50: 45777 | O50: 1
A51: ORD1047 | B51: 45861 | C51: Grace Thomas | D51: Ghana | E51: Accra | F51: fashion | G51: ELEC-1002-Y-Bluetooth Speaker | H51: 2 | I51: 300.13 | J51: 5 | K51: 570.25 | L51: Bank Transfer | M51: Delivered | N51: 45873 | O51: 1
A52: ORD1048 | B52: 45930 | C52: Ahmed Smith | D52: UK | E52: London | F52: Home & Kitchen | G52: HOME-2001-A-Air Fryer | H52: 2 | I52: 257.92 | J52: 10 | K52: 464.26 | L52: Credit Card | M52: Pending | N52: 45937 | O52: 8
A53: ORD1049 | B53: 45880 | C53: Peter Davis | D53: United Kingdom | E53: London | F53: Beauty | G53: BEAU-4001-C-Face Serum | H53: 5 | I53: 311.8 | J53: 20 | K53: 1247.2 | L53: Cash | M53: Cancelled | N53: 45883 | O53: 4
A54: ORD1050 | B54: 23/05/2025 | C54: Aisha Wilson | D54: Kenya | E54: Nairobi | F54: Beauty | G54: ELEC-1002-Y-Bluetooth Speaker | H54: 8 | I54: 289.23 | J54: 15 | K54: 1966.76 | L54: Credit-card | M54: delivered | N54: 45797 | O54: 3
A55: ORD1051 | B55: 45832 | C55: Sarah Rauf | D55: nigeria | E55: Abuja | F55: fashion | G55: BEAU-4001-C-Face Serum | H55: 5 | I55: 282.34 | J55: 20 | K55: 1129.36 | L55: PayPal | M55: Pending | N55: 45837 | O55: 2
A56: ORD1052 | B56: 45988 | C56: Ahmed Wilson | D56: Kenya | E56: Nairobi | F56: fashion | G56: FASH-3001-B-Running Shoes | H56: 0 | I56: 398.54 | J56: 0 | K56: 0 | L56: creditcard | M56: Complete | N56: 46000 | O56: 3
A57: ORD1053 | B57: 45929 | C57: Aisha Davis | D57: Nigeria | E57: Kano | F57: electronics | G57: FASH-3001-B-Running Shoes | H57: 9 | I57: 172.09 | J57: 15 | K57: 1316.49 | L57: Credit Card | M57: Shipped | N57: 45935 | O57: 3
A58: ORD1054 | B58: 46011 | C58: Aisha Johnson | D58: NIGERIA | E58: Lagos | F58: Beauty | G58: ELEC-1002-Y-Bluetooth Speaker | H58: -2 | I58: 371.92 | J58: 10 | K58: -669.46 | L58: creditcard | M58: Complete | O58: 5
A59: ORD1055 | B59: 45665 | C59: Aisha Brown | D59: South Africa | E59: Cape Town | F59: electronics | G59: BEAU-4001-C-Face Serum | H59: 3 | I59: 144.41 | J59: 0 | K59: 433.23 | L59: Cash | M59: Pending | N59: 45677 | O59: 5
A60: ORD1056 | B60: 45803 | D60: United Kingdom | E60: London | F60: Beauty | G60: FASH-3001-B-Running Shoes | H60: 8 | I60: 176.95 | J60: 0 | K60: 1415.6 | L60: Credit Card | M60: Pending | N60: 45811 | O60: 3
A61: ORD1057 | B61: 46009 | C61: Mary Anderson | D61: Kenya | E61: Nairobi | F61: Fashion | G61: ELEC-1002-Y-Bluetooth Speaker | H61: 3 | I61: 407.46 | J61: 10 | K61: 1100.14 | L61: PayPal | M61: Cancelled | N61: 46010 | O61: 1
A62: ORD1058 | B62: 45925 | C62: AHMED ANDERSON | D62: Ghana | E62: Accra | F62: Fashion | G62: FASH-3001-B-Running Shoes | H62: 8 | I62: 155.7 | J62: 20 | K62: 996.48 | L62: Credit Card | M62: Cancelled | N62: 45932 | O62: 4
A63: ORD1059 | B63: 45766 | C63: Ahmed Wilson | D63: NIGERIA | E63: Lagos | F63: Home & Kitchen | G63: ELEC-1001-X-Wireless Mouse | H63: 3 | I63: 127.53 | J63: 20 | K63: 306.07 | L63: PayPal | M63: Shipped | N63: 45771 | O63: 1
A64: ORD1060 | B64: 29/04/2025 | C64: Fatima Garcia | D64: Kenya | E64: Nairobi | F64: Electronics | G64: HOME-2001-A-Air Fryer | H64: 8 | I64: 44.88 | J64: 5 | K64: 341.09 | L64: Bank Transfer | M64: delivered | N64: 45781
A65: ORD1061 | B65: 45694 | C65: Samuel Garcia | D65: United Kingdom | E65: London | F65: Home & Kitchen | G65: ELEC-1002-Y-Bluetooth Speaker | H65: 5 | I65: 301.57 | J65: 20 | K65: 1206.28 | L65: Cash | M65: Complete | N65: 45695 | O65: 3
A66: ORD1062 | B66: 45910 | C66: Michael Taylor | D66: Ghana | E66: Accra | F66: Electronics | G66: ELEC-1001-X-Wireless Mouse | H66: 10 | I66: 29.53 | J66: 15 | K66: 251 | L66: creditcard | M66: Shipped | N66: 45918 | O66: 3
A67: ORD1063 | B67: 45953 | C67: Grace Smith | D67: NIGERIA | E67: Abuja | F67: Home & Kitchen | G67: ELEC-1002-Y-Bluetooth Speaker | H67: 8 | I67: 264.29 | J67: 15 | K67: 1797.17 | L67: Cash | M67: Pending | N67: 45954 | O67: 3
A68: ORD1064 | B68: 45828 | C68: Fatima Rauf | D68: UK | E68: London | F68: Beauty | G68: ELEC-1001-X-Wireless Mouse | H68: 3 | I68: 171.6 | J68: 15 | K68: 437.58 | L68: Bank Transfer | M68: Delivered | N68: 45834 | O68: 3
A69: ORD1065 | B69: 45823 | C69: Mary Rauf | D69: kenya | E69: Nairobi | F69: Electronics | G69: FASH-3001-B-Running Shoes | H69: 9 | I69: 414.21 | J69: 0 | K69: 3727.89 | L69: creditcard | M69: Cancelled | N69: 45825 | O69: 5
A70: ORD1066 | B70: 45658 | C70: Grace Davis | D70: Ghana | E70: Accra | F70: Home & Kitchen | G70: ELEC-1001-X-Wireless Mouse | H70: 4 | I70: 140.86 | J70: 150 | K70: -281.72 | L70: Credit Card | M70: Delivered | N70: 45897 | O70: 3
A71: ORD1067 | B71: 45817 | C71: Ahmed Wilson | D71: NIGERIA | E71: Lagos | F71: fashion | G71: ELEC-1001-X-Wireless Mouse | H71: 9 | I71: 209.92 | J71: 5 | K71: 1794.82 | L71: creditcard | M71: Pending | N71: 45826 | O71: 1
A72: ORD1068 | B72: 45870 | C72: Daniel Martin | D72: niGERIA | E72: Abuja | F72: Fashion | G72: FASH-3001-B-Running Shoes | H72: 8 | I72: 129.43 | J72: 20 | K72: 828.35 | L72: Bank Transfer | M72: Shipped | N72: 45884 | O72: 2
A73: ORD1069 | B73: 45870 | C73: sophia johnson | D73: United Kingdom | E73: London | F73: electronics | G73: BEAU-4001-C-Face Serum | H73: 5 | I73: 412.07 | J73: 10 | K73: 1854.32 | L73: PayPal | M73: Cancelled | N73: 45876 | O73: 3
A74: ORD1070 | B74: 45818 | C74: Aisha Rauf | D74: UK | E74: London | F74: Beauty | G74: FASH-3001-B-Running Shoes | H74: 6 | I74: 436.1 | J74: 5 | K74: 2485.77 | L74: PayPal | M74: Delivered | N74: 45943 | O74: 5
A75: ORD1071 | B75: 45855 | C75: Linda Davis | D75: South Africa | E75: Cape Town | F75: Electronics | G75: ELEC-1002-Y-Bluetooth Speaker | H75: 8 | I75: 482.76 | J75: 5 | K75: 3668.98 | L75: PayPal | M75: Delivered | N75: 45866 | O75: 5
A76: ORD1072 | B76: 45731 | C76: Samuel Davis | D76: UK | E76: London | F76: Electronics | G76: ELEC-1002-Y-Bluetooth Speaker | H76: -2 | I76: 240.05 | J76: 10 | K76: -432.09 | L76: Credit-card | M76: Shipped | N76: 45738 | O76: 8
... A83: ORD1079 | B83: 46006 | C83: Peter Martin | D83: United Kingdom | E83: London | F83: Fashion | G83: ELEC-1002-Y-Bluetooth Speaker | H83: 2 | I83: 452.67 | J83: 0 | K83: 905.34 | L83: Credit-card | M83: Shipped | N83: 46020 | O83: 3
A84: ORD1080 | B84: 45665 | C84: Mary Garcia | D84: nigeria | E84: Kano | F84: electronics | G84: ELEC-1002-Y-Bluetooth Speaker | H84: 3 | I84: 395.39 | J84: 10 | K84: 1067.55 | L84: Credit-card | M84: Pending | N84: 45873
A85: ORD1081 | B85: 45897 | C85: Linda Rauf | D85: South Africa | E85: Cape Town | F85: Beauty | G85: ELEC-1002-Y-Bluetooth Speaker | H85: 4 | I85: 431.47 | J85: 15 | K85: 1467 | L85: PayPal | M85: Delivered | O85: 5
A86: ORD1082 | B86: 45846 | C86: Daniel Johnson | D86: Kenya | E86: Nairobi | F86: Electronics | G86: HOME-2001-A-Air Fryer | H86: 10 | I86: 196.7 | J86: 10 | K86: 1770.3 | L86: Bank Transfer | M86: Cancelled | N86: 45857 | O86: 1
A87: ORD1083 | B87: 45989 | C87: Samuel Anderson | D87: Nigeria | E87: Lagos | F87: Electronic | G87: FASH-3001-B-Running Shoes | H87: 5 | I87: 328.13 | J87: 0 | K87: 1640.65 | L87: PayPal | M87: Delivered | N87: 45991 | O87: 2
A88: ORD1084 | B88: 45856 | D88: nigeria | E88: Kano | F88: Home & Kitchen | G88: HOME-2001-A-Air Fryer | H88: 9 | I88: 215.37 | J88: 5 | K88: 1841.41 | L88: Bank Transfer | M88: Pending | N88: 45864 | O88: 4
A89: ORD1085 | B89: 45769 | C89: John Martin | D89: South Africa | E89: Cape Town | F89: Home & Kitchen | G89: FASH-3001-B-Running Shoes | H89: 4 | I89: 429.17 | J89: 0 | K89: 1716.68 | L89: Credit-card | M89: delivered | N89: 45777 | O89: 3
A90: ORD1086 | B90: 45997 | C90: Sophia Davis | D90: NIGERIA | E90: Abuja | F90: Fashion | G90: BEAU-4001-C-Face Serum | H90: 1 | I90: 34.78 | J90: 10 | K90: 31.3 | L90: creditcard | M90: Delivered | N90: 46001 | O90: 2
A91: ORD1087 | B91: 45777 | C91: SARAH ANDERSON | D91: Ghana | E91: Accra | F91: electronics | G91: ELEC-1002-Y-Bluetooth Speaker | H91: 10 | I91: 11.39 | J91: 5 | K91: 108.2 | L91: Credit Card | M91: Shipped | N91: 45783 | O91: 2
A92: ORD1088 | B92: 45779 | C92: David Smith | D92: UK | E92: London | F92: Electronics | G92: HOME-2001-A-Air Fryer | H92: 1 | I92: 95.38 | J92: 150 | K92: -47.69 | L92: Cash | M92: Delivered | N92: 45789 | O92: 2
A93: ORD1089 | B93: 45961 | C93: Fatima Rauf | D93: Ghana | E93: Accra | F93: fashion | G93: FASH-3001-B-Running Shoes | H93: 9 | I93: 118.56 | J93: 20 | K93: 853.63 | L93: Credit Card | M93: Delivered | N93: 45963 | O93: 1
A94: ORD1090 | B94: 18/12/2025 | C94: Sophia Miller | D94: NIGERIA | E94: Lagos | F94: electronics | G94: FASH-3001-B-Running Shoes | H94: -2 | I94: 46.01 | J94: 0 | K94: -92.02 | L94: Credit-card | M94: Cancelled | N94: 46011 | O94: 3
A95: ORD1091 | B95: 45853 | C95: Daniel Martin | D95: UK | E95: London | F95: fashion | G95: BEAU-4001-C-Face Serum | H95: 5 | I95: 232.32 | J95: 20 | K95: 929.28 | L95: Credit Card | M95: Shipped | N95: 45863 | O95: 4
A96: ORD1092 | B96: 45889 | C96: linda wilson | D96: nigeria | E96: Kano | F96: Home & Kitchen | G96: FASH-3001-B-Running Shoes | H96: 6 | I96: 415.44 | J96: 15 | K96: 2118.74 | L96: Credit-card | M96: Shipped | N96: 45893 | O96: 4
A97: ORD1093 | B97: 45692 | C97: Aisha Brown | D97: Ghana | E97: Accra | F97: Fashion | G97: ELEC-1001-X-Wireless Mouse | H97: 2 | I97: 221.62 | J97: 10 | K97: 398.92 | L97: Bank Transfer | M97: Complete | N97: 45694 | O97: 2
A98: ORD1094 | B98: 45874 | C98: James Rauf | D98: Kenya | E98: Nairobi | F98: fashion | G98: ELEC-1001-X-Wireless Mouse | H98: 5 | I98: 304.2 | J98: 10 | K98: 1368.9 | L98: PayPal | M98: delivered | N98: 45888 | O98: 1
A99: ORD1095 | B99: 45716 | C99: Aisha Taylor | D99: Ghana | E99: Accra | F99: fashion | G99: HOME-2001-A-Air Fryer | H99: 10 | I99: 120.82 | J99: 15 | K99: 1026.97 | L99: Cash | M99: Complete | N99: 45729 | O99: 5
A100: ORD1096 | B100: 45831 | C100: David Garcia | D100: nigeria | E100: Abuja | F100: fashion | G100: ELEC-1001-X-Wireless Mouse | H100: 3 | I100: 436.23 | J100: 20 | K100: 1046.95 | L100: Cash | M100: Delivered | N100: 45837 | O100: 8
A101: ORD1097 | B101: 45850 | C101: Linda Taylor | D101: nigeria | E101: Lagos | F101: electronics | G101: FASH-3001-B-Running Shoes | H101: 6 | I101: 87.13 | J101: 10 | K101: 470.5 | L101: creditcard | M101: Cancelled | N101: 45857 | O101: 3
A102: ORD1098 | B102: 45884 | C102: Peter Johnson | D102: Kenya | E102: Nairobi | F102: Fashion | G102: FASH-3001-B-Running Shoes | H102: 8 | I102: 307.47 | J102: 15 | K102: 2090.8 | L102: Credit Card | M102: Complete | N102: 45895 | O102: 3
A103: ORD1099 | B103: 45658 | C103: Mary Garcia | D103: Nigeria | E103: Abuja | F103: Electronic | G103: HOME-2001-A-Air Fryer | H103: 1 | I103: 118.05 | J103: 20 | K103: 94.44 | L103: creditcard | M103: delivered | N103: 45916 | O103: 1
A104: ORD1100 | B104: 45748 | C104: Michael Rauf | D104: South Africa | E104: Cape Town | F104: Home & Kitchen | G104: FASH-3001-B-Running Shoes | H104: 3 | I104: 73.3 | J104: 20 | K104: 175.92 | L104: Cash | M104: Delivered | N104: 45658
A105: ORD1101 | B105: 45818 | C105: John Davis | D105: Kenya | E105: Nairobi | F105: Electronics | G105: FASH-3001-B-Running Shoes | H105: 10 | I105: 208.17 | J105: 15 | K105: 1769.44 | L105: Credit-card | M105: delivered | N105: 45828 | O105: 3
A106: ORD1102 | B106: 45703 | C106: Fatima Martin | D106: Kenya | E106: Nairobi | F106: Beauty | G106: ELEC-1001-X-Wireless Mouse | H106: 4 | I106: 223.48 | J106: 15 | K106: 759.83 | L106: Credit-card | M106: Shipped | N106: 45710 | O106: 5
...

Sheet Cleaned 
A1: Order ID | B1: Order Date | C1: Customer Name | D1: Country | E1: City | F1: Original Product Category | G1: Product Name | H1: Category Code | I1: Cleaned Product Category | J1: Category Match | K1: Quantity | L1: Unit Price | M1: Discount | N1: Total Sales | O1: Payment Method | P1: Order Status | Q1: Delivery Date | R1: Customer Rating | S1: Order date <= Delivery Date
A2: ORD1001 | B2: 45798 | C2: Peter Johnson | D2: Nigeria | E2: Lagos | F2: Electronics | G2: ELEC-1002-Y-Bluetooth Speaker | H2: ELEC | I2: =VLOOKUP(H2,REPORT!$B$1:$C$4,2,FALSE) -> Electronics | J2: =IF(F2=I2,"Match","Mismatch") -> Match | K2: 3 | L2: 370.87 | M2: 0.2 | N2: 890.09 | O2: Credit Card | P2: Delivered | Q2: 45802 | R2: 1 | S2: =IF(B2<=Q2,"YES","NO") -> YES
A3: ORD1002 | B3: 45945 | C3: Daniel Anderson | D3: United Kingdom | E3: London | F3: Beauty | G3: BEAU-4001-C-Face Serum | H3: BEAU | I3: =VLOOKUP(H3,REPORT!$B$1:$C$4,2,FALSE) -> Beauty | J3: =IF(F3=I3,"Match","Mismatch") -> Match | K3: 7 | L3: 118.02 | M3: 0.2 | N3: 660.91 | O3: Credit Card | P3: Shipped | Q3: 45949 | R3: 3 | S3: =IF(B3<=Q3,"YES","NO") -> YES
A4: ORD1003 | B4: 45768 | C4: Aisha Garcia | D4: Ghana | E4: Accra | F4: Electronics | G4: HOME-2001-A-Air Fryer | H4: HOME | I4: =VLOOKUP(H4,REPORT!$B$1:$C$4,2,FALSE) -> Home & Kitchen | J4: =IF(F4=I4,"Match","Mismatch") -> Mismatch | K4: 2 | L4: 55.45 | M4: 0 | N4: 110.9 | O4: Credit Card | P4: Shipped | Q4: 45781 | R4: 3 | S4: =IF(B4<=Q4,"YES","NO") -> YES
A5: ORD1004 | B5: 45932 | C5: Daniel Johnson | D5: South Africa | E5: Cape Town | F5: Electronics | G5: HOME-2001-A-Air Fryer | H5: HOME | I5: =VLOOKUP(H5,REPORT!$B$1:$C$4,2,FALSE) -> Home & Kitchen | J5: =IF(F5=I5,"Match","Mismatch") -> Mismatch | K5: 10 | L5: 443.87 | M5: 0.1 | N5: 3994.83 | O5: Credit Card | P5: Shipped | Q5: 45707 | R5: 5 | S5: =IF(B5<=Q5,"YES","NO") -> NO
A6: ORD1005 | B6: 45777 | C6: Ahmed Garcia | D6: Nigeria | E6: Kano | F6: Electronics | G6: ELEC-1001-X-Wireless Mouse | H6: ELEC | I6: =VLOOKUP(H6,REPORT!$B$1:$C$4,2,FALSE) -> Electronics | J6: =IF(F6=I6,"Match","Mismatch") -> Match | K6: 7 | L6: 146.21 | M6: 0.1 | N6: 921.12 | O6: Cash | P6: Complete | Q6: 45791 | R6: 2 | S6: =IF(B6<=Q6,"YES","NO") -> YES
A7: ORD1006 | B7: 45667 | C7: Grace Thomas | D7: Kenya | E7: Nairobi | F7: Electronics | G7: ELEC-1002-Y-Bluetooth Speaker | H7: ELEC | I7: =VLOOKUP(H7,REPORT!$B$1:$C$4,2,FALSE) -> Electronics | J7: =IF(F7=I7,"Match","Mismatch") -> Match | K7: 3 | L7: 236.51 | M7: 0.1 | N7: 638.58 | O7: Credit Card | P7: Delivered | Q7: 45943 | R7: 5 | S7: =IF(B7<=Q7,"YES","NO") -> YES
A8: ORD1007 | B8: 45795 | C8: Ahmed Rauf | D8: United Kingdom | E8: London | F8: Fashion | G8: ELEC-1002-Y-Bluetooth Speaker | H8: ELEC | I8: =VLOOKUP(H8,REPORT!$B$1:$C$4,2,FALSE) -> Electronics | J8: =IF(F8=I8,"Match","Mismatch") -> Mismatch | K8: 10 | L8: 439.42 | M8: 0.1 | N8: 3954.78 | O8: PayPal | P8: Delivered | Q8: 45797 | R8: 2 | S8: =IF(B8<=Q8,"YES","NO") -> YES
A9: ORD1008 | B9: 45726 | C9: David Wilson | D9: Kenya | E9: Nairobi | F9: Fashion | G9: BEAU-4001-C-Face Serum | H9: BEAU | I9: =VLOOKUP(H9,REPORT!$B$1:$C$4,2,FALSE) -> Beauty | J9: =IF(F9=I9,"Match","Mismatch") -> Mismatch | K9: 7 | L9: 449.93 | M9: 0.15 | N9: 2677.08 | O9: PayPal | P9: Delivered | Q9: 45938 | R9: 3 | S9: =IF(B9<=Q9,"YES","NO") -> YES
A10: ORD1009 | B10: 45979 | C10: Sophia Johnson | D10: United Kingdom | E10: London | F10: Electronics | G10: FASH-3001-B-Running Shoes | H10: FASH | I10: =VLOOKUP(H10,REPORT!$B$1:$C$4,2,FALSE) -> Fashion | J10: =IF(F10=I10,"Match","Mismatch") -> Mismatch | K10: 10 | L10: 41.13 | M10: 0.15 | N10: 349.61 | O10: Bank Transfer | P10: Delivered | Q10: 45982 | R10: 5 | S10: =IF(B10<=Q10,"YES","NO") -> YES
A11: ORD1010 | B11: 45986 | C11: Peter Taylor | D11: Ghana | E11: Accra | F11: Beauty | G11: ELEC-1001-X-Wireless Mouse | H11: ELEC | I11: =VLOOKUP(H11,REPORT!$B$1:$C$4,2,FALSE) -> Electronics | J11: =IF(F11=I11,"Match","Mismatch") -> Mismatch | K11: 5 | L11: 223.03 | M11: 0.15 | N11: 947.88 | O11: Credit Card | P11: Cancelled | Q11: 45992 | R11: 1 | S11: =IF(B11<=Q11,"YES","NO") -> YES
A12: ORD1011 | B12: 45985 | C12: Sophia Thomas | D12: Nigeria | E12: Kano | F12: Electronics | G12: BEAU-4001-C-Face Serum | H12: BEAU | I12: =VLOOKUP(H12,REPORT!$B$1:$C$4,2,FALSE) -> Beauty | J12: =IF(F12=I12,"Match","Mismatch") -> Mismatch | K12: 4 | L12: 84.89 | M12: 0.05 | N12: 322.58 | O12: PayPal | P12: Delivered | Q12: 45994 | R12: 5 | S12: =IF(B12<=Q12,"YES","NO") -> YES
A13: ORD1012 | B13: 45721 | C13: Samuel Rauf | D13: United Kingdom | E13: London | F13: Fashion | G13: ELEC-1002-Y-Bluetooth Speaker | H13: ELEC | I13: =VLOOKUP(H13,REPORT!$B$1:$C$4,2,FALSE) -> Electronics | J13: =IF(F13=I13,"Match","Mismatch") -> Mismatch | K13: 10 | L13: 474.01 | M13: 0 | N13: 4740.1 | O13: Credit Card | P13: Delivered | Q13: 45781 | R13: 4 | S13: =IF(B13<=Q13,"YES","NO") -> YES
... A20: ORD1019 | B20: 45857 | C20: David Miller | D20: Nigeria | E20: Abuja | F20: Electronics | G20: FASH-3001-B-Running Shoes | H20: FASH | I20: =VLOOKUP(H20,REPORT!$B$1:$C$4,2,FALSE) -> Fashion | J20: =IF(F20=I20,"Match","Mismatch") -> Mismatch | K20: 5 | L20: 217.27 | M20: 0.2 | N20: 869.08 | O20: Credit Card | P20: Delivered | Q20: 45862 | R20: 4 | S20: =IF(B20<=Q20,"YES","NO") -> YES
A21: ORD1020 | B21: 45818 | C21: Linda Taylor | D21: Ghana | E21: Accra | F21: Electronics | G21: ELEC-1001-X-Wireless Mouse | H21: ELEC | I21: =VLOOKUP(H21,REPORT!$B$1:$C$4,2,FALSE) -> Electronics | J21: =IF(F21=I21,"Match","Mismatch") -> Match | K21: 10 | L21: 243.63 | M21: 0.2 | N21: 1949.04 | O21: Credit Card | P21: Delivered | Q21: 45819 | S21: =IF(B21<=Q21,"YES","NO") -> YES
A22: ORD1021 | B22: 45864 | C22: Mary Thomas | D22: Kenya | E22: Nairobi | F22: Fashion | G22: BEAU-4001-C-Face Serum | H22: BEAU | I22: =VLOOKUP(H22,REPORT!$B$1:$C$4,2,FALSE) -> Beauty | J22: =IF(F22=I22,"Match","Mismatch") -> Mismatch | K22: 4 | L22: 293.67 | M22: 0 | N22: 1174.68 | O22: Bank Transfer | P22: Cancelled | Q22: 45866 | R22: 5 | S22: =IF(B22<=Q22,"YES","NO") -> YES
A23: ORD1022 | B23: 45912 | C23: Aisha Garcia | D23: United Kingdom | E23: London | F23: Beauty | G23: HOME-2001-A-Air Fryer | H23: HOME | I23: =VLOOKUP(H23,REPORT!$B$1:$C$4,2,FALSE) -> Home & Kitchen | J23: =IF(F23=I23,"Match","Mismatch") -> Mismatch | K23: 4 | L23: 140.15 | M23: 1.5 | N23: -280.3 | O23: Credit Card | P23: Delivered | Q23: 46012 | R23: 3 | S23: =IF(B23<=Q23,"YES","NO") -> YES
A24: ORD1023 | B24: 45840 | C24: Grace Anderson | D24: Nigeria | E24: Kano | F24: Electronics | G24: ELEC-1002-Y-Bluetooth Speaker | H24: ELEC | I24: =VLOOKUP(H24,REPORT!$B$1:$C$4,2,FALSE) -> Electronics | J24: =IF(F24=I24,"Match","Mismatch") -> Match | K24: 9 | L24: 139.95 | M24: 0.1 | N24: 1133.6 | O24: Credit Card | P24: Pending | Q24: 45704 | R24: 1 | S24: =IF(B24<=Q24,"YES","NO") -> NO
A25: ORD1024 | B25: 45669 | C25: Linda Garcia | D25: Ghana | E25: Accra | F25: Electronics | G25: ELEC-1001-X-Wireless Mouse | H25: ELEC | I25: =VLOOKUP(H25,REPORT!$B$1:$C$4,2,FALSE) -> Electronics | J25: =IF(F25=I25,"Match","Mismatch") -> Match | K25: 9 | L25: 156.7 | M25: 0 | N25: 1410.3 | O25: Cash | P25: Cancelled | Q25: 46001 | R25: 8 | S25: =IF(B25<=Q25,"YES","NO") -> YES
A26: ORD1025 | B26: 45765 | C26: Michael Garcia | D26: United Kingdom | E26: London | F26: Beauty | G26: HOME-2001-A-Air Fryer | H26: HOME | I26: =VLOOKUP(H26,REPORT!$B$1:$C$4,2,FALSE) -> Home & Kitchen | J26: =IF(F26=I26,"Match","Mismatch") -> Mismatch | K26: 4 | L26: 346.87 | M26: 0.1 | N26: 1248.73 | O26: Credit Card | P26: Delivered | Q26: 45762 | R26: 5 | S26: =IF(B26<=Q26,"YES","NO") -> NO
A27: ORD1026 | B27: 45658 | C27: Sophia Garcia | D27: United Kingdom | E27: London | F27: Electronics | G27: ELEC-1002-Y-Bluetooth Speaker | H27: ELEC | I27: =VLOOKUP(H27,REPORT!$B$1:$C$4,2,FALSE) -> Electronics | J27: =IF(F27=I27,"Match","Mismatch") -> Match | K27: 0 | L27: 89.18 | M27: 0.15 | N27: 0 | O27: Credit Card | P27: Delivered | Q27: 45665 | R27: 5 | S27: =IF(B27<=Q27,"YES","NO") -> YES
A28: ORD1027 | B28: 45956 | C28: Daniel Smith | D28: Nigeria | E28: Kano | F28: Electronics | G28: ELEC-1002-Y-Bluetooth Speaker | H28: ELEC | I28: =VLOOKUP(H28,REPORT!$B$1:$C$4,2,FALSE) -> Electronics | J28: =IF(F28=I28,"Match","Mismatch") -> Match | K28: 7 | L28: 72.45 | M28: 0.1 | N28: 456.44 | O28: Cash | P28: Delivered | R28: 3 | S28: =IF(B28<=Q28,"YES","NO") -> NO
A29: ORD1028 | B29: 45975 | D29: Nigeria | E29: Abuja | F29: Fashion | G29: ELEC-1002-Y-Bluetooth Speaker | H29: ELEC | I29: =VLOOKUP(H29,REPORT!$B$1:$C$4,2,FALSE) -> Electronics | J29: =IF(F29=I29,"Match","Mismatch") -> Mismatch | K29: 4 | L29: 433.66 | M29: 0.05 | N29: 1647.91 | O29: Credit Card | P29: Pending | Q29: 45987 | R29: 4 | S29: =IF(B29<=Q29,"YES","NO") -> YES
A30: ORD1006 | B30: 45667 | C30: Grace Thomas | D30: South Africa | E30: Cape Town | F30: Electronics | G30: ELEC-1002-Y-Bluetooth Speaker | H30: ELEC | I30: =VLOOKUP(H30,REPORT!$B$1:$C$4,2,FALSE) -> Electronics | J30: =IF(F30=I30,"Match","Mismatch") -> Match | K30: 3 | L30: 236.51 | M30: 0.1 | N30: 638.58 | O30: Credit Card | P30: Delivered | Q30: 45943 | R30: 5 | S30: =IF(B30<=Q30,"YES","NO") -> YES
A31: ORD1029 | B31: 45853 | C31: Michael Brown | D31: Ghana | E31: Accra | F31: Beauty | G31: ELEC-1001-X-Wireless Mouse | H31: ELEC | I31: =VLOOKUP(H31,REPORT!$B$1:$C$4,2,FALSE) -> Electronics | J31: =IF(F31=I31,"Match","Mismatch") -> Mismatch | K31: 8 | L31: 118.99 | M31: 0.15 | N31: 809.13 | O31: Credit Card | P31: Delivered | Q31: 45867 | R31: 3 | S31: =IF(B31<=Q31,"YES","NO") -> YES
A32: ORD1030 | B32: 45826 | C32: Peter Wilson | D32: South Africa | E32: Cape Town | F32: Electronics | G32: ELEC-1001-X-Wireless Mouse | H32: ELEC | I32: =VLOOKUP(H32,REPORT!$B$1:$C$4,2,FALSE) -> Electronics | J32: =IF(F32=I32,"Match","Mismatch") -> Match | K32: 5 | L32: 182.06 | M32: 0.2 | N32: 728.24 | O32: Credit Card | P32: Delivered | Q32: 45831 | R32: 4 | S32: =IF(B32<=Q32,"YES","NO") -> YES
A33: ORD1031 | B33: 45699 | C33: Michael Smith | D33: Ghana | E33: Accra | F33: Electronics | G33: HOME-2001-A-Air Fryer | H33: HOME | I33: =VLOOKUP(H33,REPORT!$B$1:$C$4,2,FALSE) -> Home & Kitchen | J33: =IF(F33=I33,"Match","Mismatch") -> Mismatch | K33: 6 | L33: 223.83 | M33: 0.2 | N33: 1074.38 | O33: Credit Card | P33: Delivered | Q33: 45970 | R33: 1 | S33: =IF(B33<=Q33,"YES","NO") -> YES
A34: ORD1032 | B34: 46009 | C34: John Taylor | D34: South Africa | E34: Cape Town | F34: Beauty | G34: ELEC-1002-Y-Bluetooth Speaker | H34: ELEC | I34: =VLOOKUP(H34,REPORT!$B$1:$C$4,2,FALSE) -> Electronics | J34: =IF(F34=I34,"Match","Mismatch") -> Mismatch | K34: 6 | L34: 221.34 | M34: 0.1 | N34: 1195.24 | O34: Credit Card | P34: Shipped | Q34: 46021 | R34: 5 | S34: =IF(B34<=Q34,"YES","NO") -> YES
A35: ORD1033 | B35: 45658 | C35: Daniel Garcia | D35: United Kingdom | E35: London | F35: Fashion | G35: FASH-3001-B-Running Shoes | H35: FASH | I35: =VLOOKUP(H35,REPORT!$B$1:$C$4,2,FALSE) -> Fashion | J35: =IF(F35=I35,"Match","Mismatch") -> Match | K35: 5 | L35: 281.66 | M35: 0.05 | N35: 1337.89 | O35: Credit Card | P35: Cancelled | Q35: 45873 | R35: 4 | S35: =IF(B35<=Q35,"YES","NO") -> YES
A36: ORD1034 | B36: 45658 | C36: Michael Miller | D36: Kenya | E36: Nairobi | F36: Home & Kitchen | G36: HOME-2001-A-Air Fryer | H36: HOME | I36: =VLOOKUP(H36,REPORT!$B$1:$C$4,2,FALSE) -> Home & Kitchen | J36: =IF(F36=I36,"Match","Mismatch") -> Match | K36: 4 | L36: 220.65 | M36: 0.2 | N36: 706.08 | O36: PayPal | P36: Shipped | Q36: 45663 | R36: 5 | S36: =IF(B36<=Q36,"YES","NO") -> YES
A37: ORD1035 | B37: 45759 | C37: Daniel Davis | D37: Nigeria | E37: Lagos | F37: Beauty | G37: HOME-2001-A-Air Fryer | H37: HOME | I37: =VLOOKUP(H37,REPORT!$B$1:$C$4,2,FALSE) -> Home & Kitchen | J37: =IF(F37=I37,"Match","Mismatch") -> Mismatch | K37: 9 | L37: 335.29 | M37: 0.2 | N37: 2414.09 | O37: Credit Card | P37: Shipped | Q37: 45997 | R37: 3 | S37: =IF(B37<=Q37,"YES","NO") -> YES
A38: ORD1036 | B38: 45670 | C38: Sarah Wilson | D38: United Kingdom | E38: London | F38: Fashion | G38: ELEC-1002-Y-Bluetooth Speaker | H38: ELEC | I38: =VLOOKUP(H38,REPORT!$B$1:$C$4,2,FALSE) -> Electronics | J38: =IF(F38=I38,"Match","Mismatch") -> Mismatch | K38: -2 | L38: 309.52 | M38: 0 | N38: -619.04 | O38: Credit Card | P38: Shipped | Q38: 45671 | R38: 4 | S38: =IF(B38<=Q38,"YES","NO") -> YES
A39: ORD1037 | B39: 45733 | C39: Fatima Miller | D39: United Kingdom | E39: London | F39: Fashion | G39: ELEC-1001-X-Wireless Mouse | H39: ELEC | I39: =VLOOKUP(H39,REPORT!$B$1:$C$4,2,FALSE) -> Electronics | J39: =IF(F39=I39,"Match","Mismatch") -> Mismatch | K39: 2 | L39: 391.43 | M39: 0.05 | N39: 743.72 | O39: Credit Card | P39: Delivered | Q39: 45744 | R39: 2 | S39: =IF(B39<=Q39,"YES","NO") -> YES
A40: ORD1038 | B40: 45929 | C40: David Davis | D40: United Kingdom | E40: London | F40: Fashion | G40: BEAU-4001-C-Face Serum | H40: BEAU | I40: =VLOOKUP(H40,REPORT!$B$1:$C$4,2,FALSE) -> Beauty | J40: =IF(F40=I40,"Match","Mismatch") -> Mismatch | K40: 6 | L40: 475.52 | M40: 0.15 | N40: 2425.15 | O40: PayPal | P40: Delivered | Q40: 45938 | R40: 5 | S40: =IF(B40<=Q40,"YES","NO") -> YES
A41: ORD1039 | B41: 45984 | C41: Fatima Garcia | D41: South Africa | E41: Cape Town | F41: Electronics | G41: BEAU-4001-C-Face Serum | H41: BEAU | I41: =VLOOKUP(H41,REPORT!$B$1:$C$4,2,FALSE) -> Beauty | J41: =IF(F41=I41,"Match","Mismatch") -> Mismatch | K41: 8 | L41: 317.11 | M41: 0.1 | N41: 2283.19 | O41: Credit Card | P41: Complete | Q41: 45989 | R41: 4 | S41: =IF(B41<=Q41,"YES","NO") -> YES
A42: ORD1040 | B42: 45728 | C42: Aisha Taylor | D42: Kenya | E42: Nairobi | F42: Electronics | G42: ELEC-1002-Y-Bluetooth Speaker | H42: ELEC | I42: =VLOOKUP(H42,REPORT!$B$1:$C$4,2,FALSE) -> Electronics | J42: =IF(F42=I42,"Match","Mismatch") -> Match | K42: 7 | L42: 350.04 | M42: 0.05 | N42: 2327.77 | O42: Bank Transfer | P42: Pending | Q42: 45731 | S42: =IF(B42<=Q42,"YES","NO") -> YES
A43: ORD1041 | B43: 45857 | C43: John Wilson | D43: Nigeria | E43: Lagos | F43: Electronics | G43: BEAU-4001-C-Face Serum | H43: BEAU | I43: =VLOOKUP(H43,REPORT!$B$1:$C$4,2,FALSE) -> Beauty | J43: =IF(F43=I43,"Match","Mismatch") -> Mismatch | K43: 1 | L43: 429.8 | M43: 0.2 | N43: 343.84 | O43: Credit Card | P43: Pending | Q43: 45870 | R43: 4 | S43: =IF(B43<=Q43,"YES","NO") -> YES
A44: ORD1042 | B44: 45788 | C44: Daniel Martin | D44: United Kingdom | E44: London | F44: Fashion | G44: FASH-3001-B-Running Shoes | H44: FASH | I44: =VLOOKUP(H44,REPORT!$B$1:$C$4,2,FALSE) -> Fashion | J44: =IF(F44=I44,"Match","Mismatch") -> Match | K44: 4 | L44: 143.74 | M44: 0.15 | N44: 488.72 | O44: Cash | P44: Pending | Q44: 45970 | R44: 1 | S44: =IF(B44<=Q44,"YES","NO") -> YES
A45: ORD1043 | B45: 45976 | C45: Sophia Davis | D45: Nigeria | E45: Abuja | F45: Beauty | G45: ELEC-1001-X-Wireless Mouse | H45: ELEC | I45: =VLOOKUP(H45,REPORT!$B$1:$C$4,2,FALSE) -> Electronics | J45: =IF(F45=I45,"Match","Mismatch") -> Mismatch | K45: 7 | L45: 300.03 | M45: 0 | N45: 2100.21 | O45: PayPal | P45: Delivered | Q45: 45985 | R45: 1 | S45: =IF(B45<=Q45,"YES","NO") -> YES
A46: ORD1044 | B46: 45766 | C46: Michael Miller | D46: United Kingdom | E46: London | F46: Beauty | G46: HOME-2001-A-Air Fryer | H46: HOME | I46: =VLOOKUP(H46,REPORT!$B$1:$C$4,2,FALSE) -> Home & Kitchen | J46: =IF(F46=I46,"Match","Mismatch") -> Mismatch | K46: 6 | L46: 383 | M46: 1.5 | N46: -1149 | O46: Credit Card | P46: Pending | Q46: 45774 | R46: 3 | S46: =IF(B46<=Q46,"YES","NO") -> YES
A47: ORD1045 | B47: 45837 | C47: Linda Taylor | D47: Ghana | E47: Accra | F47: Electronics | G47: ELEC-1001-X-Wireless Mouse | H47: ELEC | I47: =VLOOKUP(H47,REPORT!$B$1:$C$4,2,FALSE) -> Electronics | J47: =IF(F47=I47,"Match","Mismatch") -> Match | K47: 1 | L47: 379.57 | M47: 0.05 | N47: 360.59 | O47: Credit Card | P47: Delivered | Q47: 45841 | R47: 2 | S47: =IF(B47<=Q47,"YES","NO") -> YES
A48: ORD1046 | B48: 45769 | C48: Peter Johnson | D48: Nigeria | E48: Kano | F48: Electronics | G48: HOME-2001-A-Air Fryer | H48: HOME | I48: =VLOOKUP(H48,REPORT!$B$1:$C$4,2,FALSE) -> Home & Kitchen | J48: =IF(F48=I48,"Match","Mismatch") -> Mismatch | K48: 6 | L48: 92.22 | M48: 0.2 | N48: 442.66 | O48: Bank Transfer | P48: Delivered | Q48: 45777 | R48: 1 | S48: =IF(B48<=Q48,"YES","NO") -> YES
A49: ORD1047 | B49: 45861 | C49: Grace Thomas | D49: Ghana | E49: Accra | F49: Fashion | G49: ELEC-1002-Y-Bluetooth Speaker | H49: ELEC | I49: =VLOOKUP(H49,REPORT!$B$1:$C$4,2,FALSE) -> Electronics | J49: =IF(F49=I49,"Match","Mismatch") -> Mismatch | K49: 2 | L49: 300.13 | M49: 0.05 | N49: 570.25 | O49: Bank Transfer | P49: Delivered | Q49: 45873 | R49: 1 | S49: =IF(B49<=Q49,"YES","NO") -> YES
A50: ORD1048 | B50: 45930 | C50: Ahmed Smith | D50: United Kingdom | E50: London | F50: Home & Kitchen | G50: HOME-2001-A-Air Fryer | H50: HOME | I50: =VLOOKUP(H50,REPORT!$B$1:$C$4,2,FALSE) -> Home & Kitchen | J50: =IF(F50=I50,"Match","Mismatch") -> Match | K50: 2 | L50: 257.92 | M50: 0.1 | N50: 464.26 | O50: Credit Card | P50: Pending | Q50: 45937 | R50: 8 | S50: =IF(B50<=Q50,"YES","NO") -> YES
A51: ORD1049 | B51: 45969 | C51: Peter Davis | D51: United Kingdom | E51: London | F51: Beauty | G51: BEAU-4001-C-Face Serum | H51: BEAU | I51: =VLOOKUP(H51,REPORT!$B$1:$C$4,2,FALSE) -> Beauty | J51: =IF(F51=I51,"Match","Mismatch") -> Match | K51: 5 | L51: 311.8 | M51: 0.2 | N51: 1247.2 | O51: Cash | P51: Cancelled | Q51: 45883 | R51: 4 | S51: =IF(B51<=Q51,"YES","NO") -> NO
A52: ORD1050 | B52: 45800 | C52: Aisha Wilson | D52: Kenya | E52: Nairobi | F52: Beauty | G52: ELEC-1002-Y-Bluetooth Speaker | H52: ELEC | I52: =VLOOKUP(H52,REPORT!$B$1:$C$4,2,FALSE) -> Electronics | J52: =IF(F52=I52,"Match","Mismatch") -> Mismatch | K52: 8 | L52: 289.23 | M52: 0.15 | N52: 1966.76 | O52: Credit Card | P52: Delivered | Q52: 45797 | R52: 3 | S52: =IF(B52<=Q52,"YES","NO") -> NO
A53: ORD1051 | B53: 45832 | C53: Sarah Rauf | D53: Nigeria | E53: Abuja | F53: Fashion | G53: BEAU-4001-C-Face Serum | H53: BEAU | I53: =VLOOKUP(H53,REPORT!$B$1:$C$4,2,FALSE) -> Beauty | J53: =IF(F53=I53,"Match","Mismatch") -> Mismatch | K53: 5 | L53: 282.34 | M53: 0.2 | N53: 1129.36 | O53: PayPal | P53: Pending | Q53: 45837 | R53: 2 | S53: =IF(B53<=Q53,"YES","NO") -> YES
A54: ORD1052 | B54: 45988 | C54: Ahmed Wilson | D54: Kenya | E54: Nairobi | F54: Fashion | G54: FASH-3001-B-Running Shoes | H54: FASH | I54: =VLOOKUP(H54,REPORT!$B$1:$C$4,2,FALSE) -> Fashion | J54: =IF(F54=I54,"Match","Mismatch") -> Match | K54: 0 | L54: 398.54 | M54: 0 | N54: 0 | O54: Credit Card | P54: Complete | Q54: 46000 | R54: 3 | S54: =IF(B54<=Q54,"YES","NO") -> YES
A55: ORD1053 | B55: 45929 | C55: Aisha Davis | D55: Nigeria | E55: Kano | F55: Electronics | G55: FASH-3001-B-Running Shoes | H55: FASH | I55: =VLOOKUP(H55,REPORT!$B$1:$C$4,2,FALSE) -> Fashion | J55: =IF(F55=I55,"Match","Mismatch") -> Mismatch | K55: 9 | L55: 172.09 | M55: 0.15 | N55: 1316.49 | O55: Credit Card | P55: Shipped | Q55: 45935 | R55: 3 | S55: =IF(B55<=Q55,"YES","NO") -> YES
A56: ORD1054 | B56: 46011 | C56: Aisha Johnson | D56: Nigeria | E56: Lagos | F56: Beauty | G56: ELEC-1002-Y-Bluetooth Speaker | H56: ELEC | I56: =VLOOKUP(H56,REPORT!$B$1:$C$4,2,FALSE) -> Electronics | J56: =IF(F56=I56,"Match","Mismatch") -> Mismatch | K56: -2 | L56: 371.92 | M56: 0.1 | N56: -669.46 | O56: Credit Card | P56: Complete | R56: 5 | S56: =IF(B56<=Q56,"YES","NO") -> NO
A57: ORD1055 | B57: 45870 | C57: Aisha Brown | D57: South Africa | E57: Cape Town | F57: Electronics | G57: BEAU-4001-C-Face Serum | H57: BEAU | I57: =VLOOKUP(H57,REPORT!$B$1:$C$4,2,FALSE) -> Beauty | J57: =IF(F57=I57,"Match","Mismatch") -> Mismatch | K57: 3 | L57: 144.41 | M57: 0 | N57: 433.23 | O57: Cash | P57: Pending | Q57: 45677 | R57: 5 | S57: =IF(B57<=Q57,"YES","NO") -> NO
A58: ORD1056 | B58: 45803 | D58: United Kingdom | E58: London | F58: Beauty | G58: FASH-3001-B-Running Shoes | H58: FASH | I58: =VLOOKUP(H58,REPORT!$B$1:$C$4,2,FALSE) -> Fashion | J58: =IF(F58=I58,"Match","Mismatch") -> Mismatch | K58: 8 | L58: 176.95 | M58: 0 | N58: 1415.6 | O58: Credit Card | P58: Pending | Q58: 45811 | R58: 3 | S58: =IF(B58<=Q58,"YES","NO") -> YES
A59: ORD1057 | B59: 46009 | C59: Mary Anderson | D59: Kenya | E59: Nairobi | F59: Fashion | G59: ELEC-1002-Y-Bluetooth Speaker | H59: ELEC | I59: =VLOOKUP(H59,REPORT!$B$1:$C$4,2,FALSE) -> Electronics | J59: =IF(F59=I59,"Match","Mismatch") -> Mismatch | K59: 3 | L59: 407.46 | M59: 0.1 | N59: 1100.14 | O59: PayPal | P59: Cancelled | Q59: 46010 | R59: 1 | S59: =IF(B59<=Q59,"YES","NO") -> YES
A60: ORD1058 | B60: 45925 | C60: Ahmed Anderson | D60: Ghana | E60: Accra | F60: Fashion | G60: FASH-3001-B-Running Shoes | H60: FASH | I60: =VLOOKUP(H60,REPORT!$B$1:$C$4,2,FALSE) -> Fashion | J60: =IF(F60=I60,"Match","Mismatch") -> Match | K60: 8 | L60: 155.7 | M60: 0.2 | N60: 996.48 | O60: Credit Card | P60: Cancelled | Q60: 45932 | R60: 4 | S60: =IF(B60<=Q60,"YES","NO") -> YES
A61: ORD1059 | B61: 45766 | C61: Ahmed Wilson | D61: Nigeria | E61: Lagos | F61: Home & Kitchen | G61: ELEC-1001-X-Wireless Mouse | H61: ELEC | I61: =VLOOKUP(H61,REPORT!$B$1:$C$4,2,FALSE) -> Electronics | J61: =IF(F61=I61,"Match","Mismatch") -> Mismatch | K61: 3 | L61: 127.53 | M61: 0.2 | N61: 306.07 | O61: PayPal | P61: Shipped | Q61: 45771 | R61: 1 | S61: =IF(B61<=Q61,"YES","NO") -> YES
A62: ORD1060 | B62: 45776 | C62: Fatima Garcia | D62: Kenya | E62: Nairobi | F62: Electronics | G62: HOME-2001-A-Air Fryer | H62: HOME | I62: =VLOOKUP(H62,REPORT!$B$1:$C$4,2,FALSE) -> Home & Kitchen | J62: =IF(F62=I62,"Match","Mismatch") -> Mismatch | K62: 8 | L62: 44.88 | M62: 0.05 | N62: 341.09 | O62: Bank Transfer | P62: Delivered | Q62: 45781 | S62: =IF(B62<=Q62,"YES","NO") -> YES
A63: ORD1061 | B63: 45810 | C63: Samuel Garcia | D63: United Kingdom | E63: London | F63: Home & Kitchen | G63: ELEC-1002-Y-Bluetooth Speaker | H63: ELEC | I63: =VLOOKUP(H63,REPORT!$B$1:$C$4,2,FALSE) -> Electronics | J63: =IF(F63=I63,"Match","Mismatch") -> Mismatch | K63: 5 | L63: 301.57 | M63: 0.2 | N63: 1206.28 | O63: Cash | P63: Complete | Q63: 45695 | R63: 3 | S63: =IF(B63<=Q63,"YES","NO") -> NO
A64: ORD1062 | B64: 45939 | C64: Michael Taylor | D64: Ghana | E64: Accra | F64: Electronics | G64: ELEC-1001-X-Wireless Mouse | H64: ELEC | I64: =VLOOKUP(H64,REPORT!$B$1:$C$4,2,FALSE) -> Electronics | J64: =IF(F64=I64,"Match","Mismatch") -> Match | K64: 10 | L64: 29.53 | M64: 0.15 | N64: 251 | O64: Credit Card | P64: Shipped | Q64: 45918 | R64: 3 | S64: =IF(B64<=Q64,"YES","NO") -> NO
A65: ORD1063 | B65: 45953 | C65: Grace Smith | D65: Nigeria | E65: Abuja | F65: Home & Kitchen | G65: ELEC-1002-Y-Bluetooth Speaker | H65: ELEC | I65: =VLOOKUP(H65,REPORT!$B$1:$C$4,2,FALSE) -> Electronics | J65: =IF(F65=I65,"Match","Mismatch") -> Mismatch | K65: 8 | L65: 264.29 | M65: 0.15 | N65: 1797.17 | O65: Cash | P65: Pending | Q65: 45954 | R65: 3 | S65: =IF(B65<=Q65,"YES","NO") -> YES
A66: ORD1064 | B66: 45828 | C66: Fatima Rauf | D66: United Kingdom | E66: London | F66: Beauty | G66: ELEC-1001-X-Wireless Mouse | H66: ELEC | I66: =VLOOKUP(H66,REPORT!$B$1:$C$4,2,FALSE) -> Electronics | J66: =IF(F66=I66,"Match","Mismatch") -> Mismatch | K66: 3 | L66: 171.6 | M66: 0.15 | N66: 437.58 | O66: Bank Transfer | P66: Delivered | Q66: 45834 | R66: 3 | S66: =IF(B66<=Q66,"YES","NO") -> YES
A67: ORD1065 | B67: 45823 | C67: Mary Rauf | D67: Kenya | E67: Nairobi | F67: Electronics | G67: FASH-3001-B-Running Shoes | H67: FASH | I67: =VLOOKUP(H67,REPORT!$B$1:$C$4,2,FALSE) -> Fashion | J67: =IF(F67=I67,"Match","Mismatch") -> Mismatch | K67: 9 | L67: 414.21 | M67: 0 | N67: 3727.89 | O67: Credit Card | P67: Cancelled | Q67: 45825 | R67: 5 | S67: =IF(B67<=Q67,"YES","NO") -> YES
A68: ORD1066 | B68: 45658 | C68: Grace Davis | D68: Ghana | E68: Accra | F68: Home & Kitchen | G68: ELEC-1001-X-Wireless Mouse | H68: ELEC | I68: =VLOOKUP(H68,REPORT!$B$1:$C$4,2,FALSE) -> Electronics | J68: =IF(F68=I68,"Match","Mismatch") -> Mismatch | K68: 4 | L68: 140.86 | M68: 1.5 | N68: -281.72 | O68: Credit Card | P68: Delivered | Q68: 45897 | R68: 3 | S68: =IF(B68<=Q68,"YES","NO") -> YES
A69: ORD1067 | B69: 45906 | C69: Ahmed Wilson | D69: Nigeria | E69: Lagos | F69: Fashion | G69: ELEC-1001-X-Wireless Mouse | H69: ELEC | I69: =VLOOKUP(H69,REPORT!$B$1:$C$4,2,FALSE) -> Electronics | J69: =IF(F69=I69,"Match","Mismatch") -> Mismatch | K69: 9 | L69: 209.92 | M69: 0.05 | N69: 1794.82 | O69: Credit Card | P69: Pending | Q69: 45826 | R69: 1 | S69: =IF(B69<=Q69,"YES","NO") -> NO
A70: ORD1068 | B70: 45665 | C70: Daniel Martin | D70: Nigeria | E70: Abuja | F70: Fashion | G70: FASH-3001-B-Running Shoes | H70: FASH | I70: =VLOOKUP(H70,REPORT!$B$1:$C$4,2,FALSE) -> Fashion | J70: =IF(F70=I70,"Match","Mismatch") -> Match | K70: 8 | L70: 129.43 | M70: 0.2 | N70: 828.35 | O70: Bank Transfer | P70: Shipped | Q70: 45884 | R70: 2 | S70: =IF(B70<=Q70,"YES","NO") -> YES
A71: ORD1069 | B71: 45665 | C71: Sophia Johnson | D71: United Kingdom | E71: London | F71: Electronics | G71: BEAU-4001-C-Face Serum | H71: BEAU | I71: =VLOOKUP(H71,REPORT!$B$1:$C$4,2,FALSE) -> Beauty | J71: =IF(F71=I71,"Match","Mismatch") -> Mismatch | K71: 5 | L71: 412.07 | M71: 0.1 | N71: 1854.32 | O71: PayPal | P71: Cancelled | Q71: 45876 | R71: 3 | S71: =IF(B71<=Q71,"YES","NO") -> YES
A72: ORD1070 | B72: 45936 | C72: Aisha Rauf | D72: United Kingdom | E72: London | F72: Beauty | G72: FASH-3001-B-Running Shoes | H72: FASH | I72: =VLOOKUP(H72,REPORT!$B$1:$C$4,2,FALSE) -> Fashion | J72: =IF(F72=I72,"Match","Mismatch") -> Mismatch | K72: 6 | L72: 436.1 | M72: 0.05 | N72: 2485.77 | O72: PayPal | P72: Delivered | Q72: 45943 | R72: 5 | S72: =IF(B72<=Q72,"YES","NO") -> YES
A73: ORD1071 | B73: 45855 | C73: Linda Davis | D73: South Africa | E73: Cape Town | F73: Electronics | G73: ELEC-1002-Y-Bluetooth Speaker | H73: ELEC | I73: =VLOOKUP(H73,REPORT!$B$1:$C$4,2,FALSE) -> Electronics | J73: =IF(F73=I73,"Match","Mismatch") -> Match | K73: 8 | L73: 482.76 | M73: 0.05 | N73: 3668.98 | O73: PayPal | P73: Delivered | Q73: 45866 | R73: 5 | S73: =IF(B73<=Q73,"YES","NO") -> YES
A74: ORD1072 | B74: 45731 | C74: Samuel Davis | D74: United Kingdom | E74: London | F74: Electronics | G74: ELEC-1002-Y-Bluetooth Speaker | H74: ELEC | I74: =VLOOKUP(H74,REPORT!$B$1:$C$4,2,FALSE) -> Electronics | J74: =IF(F74=I74,"Match","Mismatch") -> Match | K74: -2 | L74: 240.05 | M74: 0.1 | N74: -432.09 | O74: Credit Card | P74: Shipped | Q74: 45738 | R74: 8 | S74: =IF(B74<=Q74,"YES","NO") -> YES
... A81: ORD1079 | B81: 46006 | C81: Peter Martin | D81: United Kingdom | E81: London | F81: Fashion | G81: ELEC-1002-Y-Bluetooth Speaker | H81: ELEC | I81: =VLOOKUP(H81,REPORT!$B$1:$C$4,2,FALSE) -> Electronics | J81: =IF(F81=I81,"Match","Mismatch") -> Mismatch | K81: 2 | L81: 452.67 | M81: 0 | N81: 905.34 | O81: Credit Card | P81: Shipped | Q81: 46020 | R81: 3 | S81: =IF(B81<=Q81,"YES","NO") -> YES
A82: ORD1080 | B82: 45870 | C82: Mary Garcia | D82: Nigeria | E82: Kano | F82: Electronics | G82: ELEC-1002-Y-Bluetooth Speaker | H82: ELEC | I82: =VLOOKUP(H82,REPORT!$B$1:$C$4,2,FALSE) -> Electronics | J82: =IF(F82=I82,"Match","Mismatch") -> Match | K82: 3 | L82: 395.39 | M82: 0.1 | N82: 1067.55 | O82: Credit Card | P82: Pending | Q82: 45873 | S82: =IF(B82<=Q82,"YES","NO") -> YES
A83: ORD1081 | B83: 45897 | C83: Linda Rauf | D83: South Africa | E83: Cape Town | F83: Beauty | G83: ELEC-1002-Y-Bluetooth Speaker | H83: ELEC | I83: =VLOOKUP(H83,REPORT!$B$1:$C$4,2,FALSE) -> Electronics | J83: =IF(F83=I83,"Match","Mismatch") -> Mismatch | K83: 4 | L83: 431.47 | M83: 0.15 | N83: 1467 | O83: PayPal | P83: Delivered | R83: 5 | S83: =IF(B83<=Q83,"YES","NO") -> NO
A84: ORD1082 | B84: 45876 | C84: Daniel Johnson | D84: Kenya | E84: Nairobi | F84: Electronics | G84: HOME-2001-A-Air Fryer | H84: HOME | I84: =VLOOKUP(H84,REPORT!$B$1:$C$4,2,FALSE) -> Home & Kitchen | J84: =IF(F84=I84,"Match","Mismatch") -> Mismatch | K84: 10 | L84: 196.7 | M84: 0.1 | N84: 1770.3 | O84: Bank Transfer | P84: Cancelled | Q84: 45857 | R84: 1 | S84: =IF(B84<=Q84,"YES","NO") -> NO
A85: ORD1083 | B85: 45989 | C85: Samuel Anderson | D85: Nigeria | E85: Lagos | F85: Electronics | G85: FASH-3001-B-Running Shoes | H85: FASH | I85: =VLOOKUP(H85,REPORT!$B$1:$C$4,2,FALSE) -> Fashion | J85: =IF(F85=I85,"Match","Mismatch") -> Mismatch | K85: 5 | L85: 328.13 | M85: 0 | N85: 1640.65 | O85: PayPal | P85: Delivered | Q85: 45991 | R85: 2 | S85: =IF(B85<=Q85,"YES","NO") -> YES
A86: ORD1084 | B86: 45856 | D86: Nigeria | E86: Kano | F86: Home & Kitchen | G86: HOME-2001-A-Air Fryer | H86: HOME | I86: =VLOOKUP(H86,REPORT!$B$1:$C$4,2,FALSE) -> Home & Kitchen | J86: =IF(F86=I86,"Match","Mismatch") -> Match | K86: 9 | L86: 215.37 | M86: 0.05 | N86: 1841.41 | O86: Bank Transfer | P86: Pending | Q86: 45864 | R86: 4 | S86: =IF(B86<=Q86,"YES","NO") -> YES
A87: ORD1085 | B87: 45769 | C87: John Martin | D87: South Africa | E87: Cape Town | F87: Home & Kitchen | G87: FASH-3001-B-Running Shoes | H87: FASH | I87: =VLOOKUP(H87,REPORT!$B$1:$C$4,2,FALSE) -> Fashion | J87: =IF(F87=I87,"Match","Mismatch") -> Mismatch | K87: 4 | L87: 429.17 | M87: 0 | N87: 1716.68 | O87: Credit Card | P87: Delivered | Q87: 45777 | R87: 3 | S87: =IF(B87<=Q87,"YES","NO") -> YES
A88: ORD1086 | B88: 45820 | C88: Sophia Davis | D88: Nigeria | E88: Abuja | F88: Fashion | G88: BEAU-4001-C-Face Serum | H88: BEAU | I88: =VLOOKUP(H88,REPORT!$B$1:$C$4,2,FALSE) -> Beauty | J88: =IF(F88=I88,"Match","Mismatch") -> Mismatch | K88: 1 | L88: 34.78 | M88: 0.1 | N88: 31.3 | O88: Credit Card | P88: Delivered | Q88: 46001 | R88: 2 | S88: =IF(B88<=Q88,"YES","NO") -> YES
A89: ORD1087 | B89: 45777 | C89: Sarah Anderson | D89: Ghana | E89: Accra | F89: Electronics | G89: ELEC-1002-Y-Bluetooth Speaker | H89: ELEC | I89: =VLOOKUP(H89,REPORT!$B$1:$C$4,2,FALSE) -> Electronics | J89: =IF(F89=I89,"Match","Mismatch") -> Match | K89: 10 | L89: 11.39 | M89: 0.05 | N89: 108.2 | O89: Credit Card | P89: Shipped | Q89: 45783 | R89: 2 | S89: =IF(B89<=Q89,"YES","NO") -> YES
A90: ORD1088 | B90: 45693 | C90: David Smith | D90: United Kingdom | E90: London | F90: Electronics | G90: HOME-2001-A-Air Fryer | H90: HOME | I90: =VLOOKUP(H90,REPORT!$B$1:$C$4,2,FALSE) -> Home & Kitchen | J90: =IF(F90=I90,"Match","Mismatch") -> Mismatch | K90: 1 | L90: 95.38 | M90: 1.5 | N90: -47.69 | O90: Cash | P90: Delivered | Q90: 45789 | R90: 2 | S90: =IF(B90<=Q90,"YES","NO") -> YES
A91: ORD1089 | B91: 45961 | C91: Fatima Rauf | D91: Ghana | E91: Accra | F91: Fashion | G91: FASH-3001-B-Running Shoes | H91: FASH | I91: =VLOOKUP(H91,REPORT!$B$1:$C$4,2,FALSE) -> Fashion | J91: =IF(F91=I91,"Match","Mismatch") -> Match | K91: 9 | L91: 118.56 | M91: 0.2 | N91: 853.63 | O91: Credit Card | P91: Delivered | Q91: 45963 | R91: 1 | S91: =IF(B91<=Q91,"YES","NO") -> YES
A92: ORD1090 | B92: 46009 | C92: Sophia Miller | D92: Nigeria | E92: Lagos | F92: Electronics | G92: FASH-3001-B-Running Shoes | H92: FASH | I92: =VLOOKUP(H92,REPORT!$B$1:$C$4,2,FALSE) -> Fashion | J92: =IF(F92=I92,"Match","Mismatch") -> Mismatch | K92: -2 | L92: 46.01 | M92: 0 | N92: -92.02 | O92: Credit Card | P92: Cancelled | Q92: 46011 | R92: 3 | S92: =IF(B92<=Q92,"YES","NO") -> YES
A93: ORD1091 | B93: 45853 | C93: Daniel Martin | D93: United Kingdom | E93: London | F93: Fashion | G93: BEAU-4001-C-Face Serum | H93: BEAU | I93: =VLOOKUP(H93,REPORT!$B$1:$C$4,2,FALSE) -> Beauty | J93: =IF(F93=I93,"Match","Mismatch") -> Mismatch | K93: 5 | L93: 232.32 | M93: 0.2 | N93: 929.28 | O93: Credit Card | P93: Shipped | Q93: 45863 | R93: 4 | S93: =IF(B93<=Q93,"YES","NO") -> YES
A94: ORD1092 | B94: 45889 | C94: Linda Wilson | D94: Nigeria | E94: Kano | F94: Home & Kitchen | G94: FASH-3001-B-Running Shoes | H94: FASH | I94: =VLOOKUP(H94,REPORT!$B$1:$C$4,2,FALSE) -> Fashion | J94: =IF(F94=I94,"Match","Mismatch") -> Mismatch | K94: 6 | L94: 415.44 | M94: 0.15 | N94: 2118.74 | O94: Credit Card | P94: Shipped | Q94: 45893 | R94: 4 | S94: =IF(B94<=Q94,"YES","NO") -> YES
A95: ORD1093 | B95: 45749 | C95: Aisha Brown | D95: Ghana | E95: Accra | F95: Fashion | G95: ELEC-1001-X-Wireless Mouse | H95: ELEC | I95: =VLOOKUP(H95,REPORT!$B$1:$C$4,2,FALSE) -> Electronics | J95: =IF(F95=I95,"Match","Mismatch") -> Mismatch | K95: 2 | L95: 221.62 | M95: 0.1 | N95: 398.92 | O95: Bank Transfer | P95: Complete | Q95: 45694 | R95: 2 | S95: =IF(B95<=Q95,"YES","NO") -> NO
A96: ORD1094 | B96: 45785 | C96: James Rauf | D96: Kenya | E96: Nairobi | F96: Fashion | G96: ELEC-1001-X-Wireless Mouse | H96: ELEC | I96: =VLOOKUP(H96,REPORT!$B$1:$C$4,2,FALSE) -> Electronics | J96: =IF(F96=I96,"Match","Mismatch") -> Mismatch | K96: 5 | L96: 304.2 | M96: 0.1 | N96: 1368.9 | O96: PayPal | P96: Delivered | Q96: 45888 | R96: 1 | S96: =IF(B96<=Q96,"YES","NO") -> YES
A97: ORD1095 | B97: 45716 | C97: Aisha Taylor | D97: Ghana | E97: Accra | F97: Fashion | G97: HOME-2001-A-Air Fryer | H97: HOME | I97: =VLOOKUP(H97,REPORT!$B$1:$C$4,2,FALSE) -> Home & Kitchen | J97: =IF(F97=I97,"Match","Mismatch") -> Mismatch | K97: 10 | L97: 120.82 | M97: 0.15 | N97: 1026.97 | O97: Cash | P97: Complete | Q97: 45729 | R97: 5 | S97: =IF(B97<=Q97,"YES","NO") -> YES
A98: ORD1096 | B98: 45831 | C98: David Garcia | D98: Nigeria | E98: Abuja | F98: Fashion | G98: ELEC-1001-X-Wireless Mouse | H98: ELEC | I98: =VLOOKUP(H98,REPORT!$B$1:$C$4,2,FALSE) -> Electronics | J98: =IF(F98=I98,"Match","Mismatch") -> Mismatch | K98: 3 | L98: 436.23 | M98: 0.2 | N98: 1046.95 | O98: Cash | P98: Delivered | Q98: 45837 | R98: 8 | S98: =IF(B98<=Q98,"YES","NO") -> YES
... A101: ORD1099 | B101: 45658 | C101: Mary Garcia | D101: Nigeria | E101: Abuja | F101: Electronics | G101: HOME-2001-A-Air Fryer | H101: HOME | I101: =VLOOKUP(H101,REPORT!$B$1:$C$4,2,FALSE) -> Home & Kitchen | J101: =IF(F101=I101,"Match","Mismatch") -> Mismatch | K101: 1 | L101: 118.05 | M101: 0.2 | N101: 94.44 | O101: Credit Card | P101: Delivered | Q101: 45916 | R101: 1 | S101: =IF(B101<=Q101,"YES","NO") -> YES
A102: ORD1100 | B102: 45661 | C102: Michael Rauf | D102: South Africa | E102: Cape Town | F102: Home & Kitchen | G102: FASH-3001-B-Running Shoes | H102: FASH | I102: =VLOOKUP(H102,REPORT!$B$1:$C$4,2,FALSE) -> Fashion | J102: =IF(F102=I102,"Match","Mismatch") -> Mismatch | K102: 3 | L102: 73.3 | M102: 0.2 | N102: 175.92 | O102: Cash | P102: Delivered | Q102: 45658 | S102: =IF(B102<=Q102,"YES","NO") -> NO
A103: ORD1101 | B103: 45936 | C103: John Davis | D103: Kenya | E103: Nairobi | F103: Electronics | G103: FASH-3001-B-Running Shoes | H103: FASH | I103: =VLOOKUP(H103,REPORT!$B$1:$C$4,2,FALSE) -> Fashion | J103: =IF(F103=I103,"Match","Mismatch") -> Mismatch | K103: 10 | L103: 208.17 | M103: 0.15 | N103: 1769.44 | O103: Credit Card | P103: Delivered | Q103: 45828 | R103: 3 | S103: =IF(B103<=Q103,"YES","NO") -> NO
A104: ORD1102 | B104: 45703 | C104: Fatima Martin | D104: Kenya | E104: Nairobi | F104: Beauty | G104: ELEC-1001-X-Wireless Mouse | H104: ELEC | I104: =VLOOKUP(H104,REPORT!$B$1:$C$4,2,FALSE) -> Electronics | J104: =IF(F104=I104,"Match","Mismatch") -> Mismatch | K104: 4 | L104: 223.48 | M104: 0.15 | N104: 759.83 | O104: Credit Card | P104: Shipped | Q104: 45710 | R104: 5 | S104: =IF(B104<=Q104,"YES","NO") -> YES
A105: ORD1103 | B105: 45902 | C105: Sarah Rauf | D105: Nigeria | E105: Abuja | F105: Electronics | G105: ELEC-1001-X-Wireless Mouse | H105: ELEC | I105: =VLOOKUP(H105,REPORT!$B$1:$C$4,2,FALSE) -> Electronics | J105: =IF(F105=I105,"Match","Mismatch") -> Match | K105: 9 | L105: 259.88 | M105: 0.1 | N105: 2105.03 | O105: Credit Card | P105: Complete | Q105: 45706 | R105: 3 | S105: =IF(B105<=Q105,"YES","NO") -> NO
A106: ORD1104 | B106: 45993 | C106: David Anderson | D106: United Kingdom | E106: London | F106: Fashion | G106: ELEC-1002-Y-Bluetooth Speaker | H106: ELEC | I106: =VLOOKUP(H106,REPORT!$B$1:$C$4,2,FALSE) -> Electronics | J106: =IF(F106=I106,"Match","Mismatch") -> Mismatch | K106: 0 | L106: 237.34 | M106: 0.2 | N106: 0 | O106: Cash | P106: Shipped | Q106: 45995 | R106: 5 | S106: =IF(B106<=Q106,"YES","NO") -> YES
A107: ORD1105 | B107: 45735 | C107: Aisha Thomas | D107: Nigeria | E107: Kano | F107: Fashion | G107: ELEC-1001-X-Wireless Mouse | H107: ELEC | I107: =VLOOKUP(H107,REPORT!$B$1:$C$4,2,FALSE) -> Electronics | J107: =IF(F107=I107,"Match","Mismatch") -> Mismatch | K107: 8 | L107: 226.68 | M107: 0.1 | N107: 1632.1 | O107: Credit Card | P107: Complete | Q107: 45743 | R107: 3 | S107: =IF(B107<=Q107,"YES","NO") -> YES
A108: ORD1106 | B108: 45876 | C108: Fatima Smith | D108: United Kingdom | E108: London | F108: Fashion | G108: HOME-2001-A-Air Fryer | H108: HOME | I108: =VLOOKUP(H108,REPORT!$B$1:$C$4,2,FALSE) -> Home & Kitchen | J108: =IF(F108=I108,"Match","Mismatch") -> Mismatch | K108: 2 | L108: 325.89 | M108: 0 | N108: 651.78 | O108: Bank Transfer | P108: Shipped | Q108: 45860 | R108: 5 | S108: =IF(B108<=Q108,"YES","NO") -> NO
A109: ORD1107 | B109: 45842 | C109: Fatima Anderson | D109: Nigeria | E109: Lagos | F109: Beauty | G109: BEAU-4001-C-Face Serum | H109: BEAU | I109: =VLOOKUP(H109,REPORT!$B$1:$C$4,2,FALSE) -> Beauty | J109: =IF(F109=I109,"Match","Mismatch") -> Match | K109: 8 | L109: 255.67 | M109: 0 | N109: 2045.36 | O109: Credit Card | P109: Shipped | Q109: 45760 | R109: 4 | S109: =IF(B109<=Q109,"YES","NO") -> NO
A110: ORD1108 | B110: 45678 | C110: Daniel Thomas | D110: South Africa | E110: Cape Town | F110: Electronics | G110: FASH-3001-B-Running Shoes | H110: FASH | I110: =VLOOKUP(H110,REPORT!$B$1:$C$4,2,FALSE) -> Fashion | J110: =IF(F110=I110,"Match","Mismatch") -> Mismatch | K110: -2 | L110: 266.79 | M110: 0.2 | N110: -426.86 | O110: PayPal | P110: Pending | R110: 2 | S110: =IF(B110<=Q110,"YES","NO") -> NO
A111: ORD1109 | B111: 45981 | C111: Peter Anderson | D111: Ghana | E111: Accra | F111: Fashion | G111: HOME-2001-A-Air Fryer | H111: HOME | I111: =VLOOKUP(H111,REPORT!$B$1:$C$4,2,FALSE) -> Home & Kitchen | J111: =IF(F111=I111,"Match","Mismatch") -> Mismatch | K111: 2 | L111: 171.55 | M111: 0.2 | N111: 274.48 | O111: Cash | P111: Cancelled | Q111: 45992 | R111: 4 | S111: =IF(B111<=Q111,"YES","NO") -> YES
A112: ORD1110 | B112: 45997 | C112: Aisha Johnson | D112: Nigeria | E112: Kano | F112: Fashion | G112: HOME-2001-A-Air Fryer | H112: HOME | I112: =VLOOKUP(H112,REPORT!$B$1:$C$4,2,FALSE) -> Home & Kitchen | J112: =IF(F112=I112,"Match","Mismatch") -> Mismatch | K112: 5 | L112: 484.17 | M112: 1.5 | N112: -1210.42 | O112: PayPal | P112: Shipped | Q112: 46000 | R112: 2 | S112: =IF(B112<=Q112,"YES","NO") -> YES
A113: ORD1111 | B113: 46017 | C113: Sophia Brown | D113: South Africa | E113: Cape Town | F113: Electronics | G113: BEAU-4001-C-Face Serum | H113: BEAU | I113: =VLOOKUP(H113,REPORT!$B$1:$C$4,2,FALSE) -> Beauty | J113: =IF(F113=I113,"Match","Mismatch") -> Mismatch | K113: 2 | L113: 326.55 | M113: 0.15 | N113: 555.13 | O113: Credit Card | P113: Delivered | Q113: 46031 | R113: 5 | S113: =IF(B113<=Q113,"YES","NO") -> YES
A114: ORD1112 | B114: 45773 | D114: Nigeria | E114: Lagos | F114: Electronics | G114: ELEC-1002-Y-Bluetooth Speaker | H114: ELEC | I114: =VLOOKUP(H114,REPORT!$B$1:$C$4,2,FALSE) -> Electronics | J114: =IF(F114=I114,"Match","Mismatch") -> Match | K114: 2 | L114: 154.94 | M114: 0 | N114: 309.88 | O114: Bank Transfer | P114: Delivered | Q114: 45776 | R114: 5 | S114: =IF(B114<=Q114,"YES","NO") -> YES
...

Sheet REPORT
B1: ELEC | C1: Electronics
B2: BEAU | C2: Beauty
B3: FASH | C3: Fashion
B4: HOME | C4: Home & Kitchen
